msdbook/__init__.py
msdbook/fishery_dynamics.py
msdbook/generalized_fish_game.py
msdbook/hymod.py
msdbook/install_supplement.py
msdbook/package_data.py
msdbook/utils.py
msdbook/tests/__init__.py
msdbook/tests/test_fishery_dynamics.py
msdbook/tests/test_hymod.py
msdbook/tests/test_install_supplement.py
msdbook/tests/test_package_data.py
msdbook-0.1.6.dist-info/METADATA
msdbook-0.1.6.dist-info/WHEEL
msdbook-0.1.6.dist-info/licenses/LICENSE
msdbook-0.1.6.dist-info/RECORD
